LICENSE
README.md
setup.cfg
setup.py
PuJian_KeJi_UserCenter_Api.egg-info/PKG-INFO
PuJian_KeJi_UserCenter_Api.egg-info/SOURCES.txt
PuJian_KeJi_UserCenter_Api.egg-info/dependency_links.txt
PuJian_KeJi_UserCenter_Api.egg-info/top_level.txt
userCenterApi/__init__.py
userCenterApi/api.py
userCenterApi/base.py
userCenterApi/url_settings.py
userCenterApi/utils.py